token_shift_gpt/__init__.py
token_shift_gpt/autoregressive_wrapper.py
token_shift_gpt/token_shift_gpt.py
token_shift_gpt-0.0.2.dist-info/LICENSE
token_shift_gpt-0.0.2.dist-info/METADATA
token_shift_gpt-0.0.2.dist-info/WHEEL
token_shift_gpt-0.0.2.dist-info/top_level.txt
token_shift_gpt-0.0.2.dist-info/RECORD
