Metadata-Version: 2.1
Name: token-shift-gpt
Version: 0.0.2
Summary: Token Shift GPT - Pytorch
Home-page: https://github.com/lucidrains/token-shift-gpt
Author: Phil Wang
Author-email: lucidrains@gmail.com
License: MIT
Keywords: artificial intelligence,deep learning,autoregressive language modeling
Platform: UNKNOWN
Classifier: Development Status :: 4 - Beta
Classifier: Intended Audience :: Developers
Classifier: Topic :: Scientific/Engineering :: Artificial Intelligence
Classifier: License :: OSI Approved :: MIT License
Classifier: Programming Language :: Python :: 3.6
License-File: LICENSE
Requires-Dist: einops (>=0.3)
Requires-Dist: torch (>=1.6)
